README.md
setup.py
pyjr/__init__.py
pyjr.egg-info/PKG-INFO
pyjr.egg-info/SOURCES.txt
pyjr.egg-info/dependency_links.txt
pyjr.egg-info/top_level.txt
pyjr/classes/__init__.py
pyjr/classes/data.py
pyjr/classes/features.py
pyjr/classes/model_data.py
pyjr/classes/preprocess_data.py
pyjr/classes/stat.py
pyjr/classes/timeseries.py
pyjr/classes/tuning.py
pyjr/models/__init__.py
pyjr/models/classification.py
pyjr/models/cluster.py
pyjr/models/regression.py
pyjr/models/simple_regression.py
pyjr/plot/__init__.py
pyjr/plot/barchart.py
pyjr/plot/histogram.py
pyjr/plot/line.py
pyjr/plot/scatter.py
pyjr/plot/table.py
pyjr/utils/__init__.py
pyjr/utils/_class_functions.py
pyjr/utils/evaluate.py
pyjr/utils/simple.py
pyjr/utils/tools/__init__.py
pyjr/utils/tools/array.py
pyjr/utils/tools/clean.py
pyjr/utils/tools/dataframe.py
pyjr/utils/tools/dic.py
pyjr/utils/tools/general.py
pyjr/utils/tools/math.py