Metadata-Version: 2.1
Name: pyjr
Version: 0.1.0
Summary: Functions and Classes for assisting with ETL.
Home-page: UNKNOWN
Author: Peter Rigali
Author-email: peterjrigali@gmail.com
License: MIT
Platform: UNKNOWN
